Metadata-Version: 1.0
Name: scrapy-redis-nonempty-run
Version: 1.6
Summary: deal with scrapy-redis's the problem of empty run
Home-page: https://github.com/xiaoyangjie/scrapy-redis-noemptyrun
Author: yangyuya
Author-email: 1019177406@qq.com
License: MIT Licence
Keywords: pip,scrapy-redis-nonempty_run
Platform: any
